units_converter/__init__.py
units_converter/main.py
units_converter/version.py
units_converter-0.0.1.dist-info/LICENSE
units_converter-0.0.1.dist-info/METADATA
units_converter-0.0.1.dist-info/WHEEL
units_converter-0.0.1.dist-info/top_level.txt
units_converter-0.0.1.dist-info/RECORD
